LICENSE.txt
MANIFEST.in
README.txt
metadata.py
setup.cfg
setup.py
django_urlprepend.egg-info/PKG-INFO
django_urlprepend.egg-info/SOURCES.txt
django_urlprepend.egg-info/dependency_links.txt
django_urlprepend.egg-info/top_level.txt
docs/history.rst
docs/index.rst
docs/setup.rst
docs/usage.rst
urlprepend/__init__.py
urlprepend/context_processors.py
urlprepend/middleware.py
urlprepend/settings.py
urlprepend/utils.py