Metadata-Version: 1.1
Name: django-urlprepend
Version: 0.4.6
Summary: This Django application you to prepend a string to your django app urls useful if you need to change themes based on url.
Home-page: UNKNOWN
Author: Philip Roche
Author-email: phil.roche@ticket-text.com
License: MIT License
Keywords: django url
Platform: UNKNOWN
Classifier: Development Status :: 4 - Beta
Classifier: Environment :: Web Environment
Classifier: Framework :: Django
Classifier: Intended Audience :: Developers
Classifier: License :: OSI Approved :: MIT License
Classifier: Operating System :: OS Independent
Classifier: Programming Language :: Python
Classifier: Topic :: Software Development :: Libraries :: Application Frameworks
Classifier: Topic :: Software Development :: Libraries :: Python Modules
Classifier: Topic :: Internet :: WWW/HTTP :: WSGI :: Middleware
